{
  "schemaVersion": 1,
  "id": "corntopia",
  "version": "${version}",
  "name": "Corntopia",
  "description": "Corn and corn related features!",
  "authors": [
    "Colton Loewen"
  ],
  "contact": {
    "homepage": "https://cjloewen.ca/",
    "issues": "https://github.com/cloewen8/Corntopia/issues/new/choose",
    "sources": "https://github.com/cloewen8/Corntopia"
  },

  "license": "Apache-2.0",
  "icon": "assets/corntopia/icon.png",

  "environment": "*",
  "entrypoints": {
    "main": [
      "ca.cjloewen.corntopia.CorntopiaMod"
    ]
  },

  "depends": {
    "fabricloader": ">=0.7.4",
    "fabric": "*",
    "minecraft": "1.16.x"
  },
  "mixins": [
  	"corntopia.mixins.json"
  ]
}
